mcp_server_sql_analyzer/__init__.py
mcp_server_sql_analyzer/server.py
iflow_mcp_j4c0bs_mcp_server_sql_analyzer-0.1.0.dist-info/METADATA
iflow_mcp_j4c0bs_mcp_server_sql_analyzer-0.1.0.dist-info/WHEEL
iflow_mcp_j4c0bs_mcp_server_sql_analyzer-0.1.0.dist-info/entry_points.txt
iflow_mcp_j4c0bs_mcp_server_sql_analyzer-0.1.0.dist-info/licenses/LICENSE
iflow_mcp_j4c0bs_mcp_server_sql_analyzer-0.1.0.dist-info/RECORD
