Metadata-Version: 2.4
Name: iflow-mcp_j4c0bs_mcp-server-sql-analyzer
Version: 0.1.0
Summary: SQL analyzer server for MCP
License-File: LICENSE
Requires-Python: >=3.12
Requires-Dist: mcp>=1.2.0
Requires-Dist: pydantic>=2.10.6
Requires-Dist: sqlglot>=26.2.1
